{
  "bootloader": {
    "prefixInfo": {
      "moduleStartAddy": "f4000",
      "moduleEndAddy": "ffdbe",
      "reserved": 0,
      "moduleFlags": 0,
      "moduleVersion": 3300,
      "platformID": 25,
      "moduleFunction": 2,
      "moduleIndex": 0,
      "depModuleFunction": 0,
      "depModuleIndex": 0,
      "depModuleVersion": 0,
      "dep2ModuleFunction": 0,
      "dep2ModuleIndex": 0,
      "dep2ModuleVersion": 0,
      "prefixSize": 24,
      "prefixOffset": 512
    },
    "suffixInfo": {
      "productId": 0,
      "productVersion": 0,
      "fwUniqueId": "d1decb915ce7619ac64cf85e7f4841adfd74881cb496608bac0932dad6c418e9",
      "reserved": 0,
      "suffixSize": 40,
      "crcBlock": "90b35347"
    }
  },
  "softdevice": {
    "prefixInfo": {
      "moduleStartAddy": "1000",
      "moduleEndAddy": "265d4",
      "reserved": 0,
      "moduleFlags": 1,
      "moduleVersion": 202,
      "platformID": 25,
      "moduleFunction": 8,
      "moduleIndex": 0,
      "depModuleFunction": 2,
      "depModuleIndex": 0,
      "depModuleVersion": 501,
      "dep2ModuleFunction": 4,
      "dep2ModuleIndex": 1,
      "dep2ModuleVersion": 1321,
      "prefixSize": 24,
      "prefixOffset": 0
    },
    "suffixInfo": {
      "productId": -1,
      "productVersion": -1,
      "fwUniqueId": "939fee60b4b8dcb8cf25533a46ba8774c418174b80d5fad5e1f89064c04d8bb4",
      "reserved": 0,
      "suffixSize": 36,
      "crcBlock": "62e9b43b"
    }
  },
  "system-part1": {
    "prefixInfo": {
      "moduleStartAddy": "28000",
      "moduleEndAddy": "b2944",
      "reserved": 0,
      "moduleFlags": 0,
      "moduleVersion": 6400,
      "platformID": 25,
      "moduleFunction": 4,
      "moduleIndex": 1,
      "depModuleFunction": 2,
      "depModuleIndex": 0,
      "depModuleVersion": 3100,
      "dep2ModuleFunction": 8,
      "dep2ModuleIndex": 0,
      "dep2ModuleVersion": 202,
      "prefixSize": 24,
      "prefixOffset": 512
    },
    "suffixInfo": {
      "productId": 0,
      "productVersion": 0,
      "fwUniqueId": "70daf0205d994ffb4308919e4d6535d77e0e918662b6c9693e60807ac02e9475",
      "reserved": 0,
      "suffixSize": 40,
      "crcBlock": "fcc83140"
    }
  },
  "tinker": {
    "prefixInfo": {
      "moduleStartAddy": "b4000",
      "moduleEndAddy": "b6b3e",
      "reserved": 0,
      "moduleFlags": 0,
      "moduleVersion": 10,
      "platformID": 25,
      "moduleFunction": 5,
      "moduleIndex": 2,
      "depModuleFunction": 4,
      "depModuleIndex": 1,
      "depModuleVersion": 6400,
      "dep2ModuleFunction": 0,
      "dep2ModuleIndex": 0,
      "dep2ModuleVersion": 0,
      "prefixSize": 24,
      "prefixOffset": 0
    },
    "suffixInfo": {
      "productId": 25,
      "productVersion": 3,
      "fwUniqueId": "20b601214c3b59f1ba2b3035b540569da602b3642c7faa17d05541c9759406af",
      "reserved": 0,
      "suffixSize": 40,
      "crcBlock": "4cfa1c24"
    }
  }
}