{
  "type": "libraries",
  "id": "Adafruit_Mini_GPS_PA1010D",
  "links": {
    "download": "https://api.particle.io/v1/libraries/Adafruit_Mini_GPS_PA1010D/archive/1.7.5.tar.gz"
  },
  "attributes": {
    "name": "Adafruit_Mini_GPS_PA1010D",
    "version": "1.7.5",
    "author": "Adafruit",
    "maintainer": "Adafruit <info@adafruit.com>",
    "sentence": "An interrupt-based GPS library for no-parsing-required use",
    "paragraph": "An interrupt-based GPS library for no-parsing-required use",
    "category": "Sensors",
    "url": "https://github.com/adafruit/Adafruit_GPS",
    "architectures": [
      "*"
    ],
    "visibility": "public",
    "mine": false
  },
  "kind": "community library",
  "letter": "a",
  "cardUrl": "/reference/device-os/libraries/a/Adafruit_Mini_GPS_PA1010D",
  "versions": {
    "1.7.5": {
      "added": "2026-02-02T09:49:30.685Z",
      "builds": {
        "6.2.0": {
          "boron": {
            "GPS_HardwareSerial_EchoTest": true,
            "GPS_HardwareSerial_LOCUS_DumpBasic": true,
            "GPS_HardwareSerial_LOCUS_Erase": true,
            "GPS_HardwareSerial_LOCUS_Start": true,
            "GPS_HardwareSerial_LOCUS_Status": true,
            "GPS_HardwareSerial_Parsing": true,
            "GPS_HardwareSerial_Timing": true,
            "GPS_I2C_EchoTest": true,
            "GPS_I2C_OLEDdebug": true,
            "GPS_I2C_Parsing": true,
            "GPS_SPI_EchoTest": true,
            "GPS_SoftwareSerial_EchoTest": false,
            "GPS_SoftwareSerial_LOCUS_DumpBasic": false,
            "GPS_SoftwareSerial_LOCUS_Erase": false,
            "GPS_SoftwareSerial_LOCUS_Start": false,
            "GPS_SoftwareSerial_LOCUS_Status": false,
            "GPS_SoftwareSerial_Parsing": false,
            "NMEA_EXTENSIONS": true,
            "blank": true,
            "shield_sdlog": false
          },
          "bsom": {
            "GPS_HardwareSerial_EchoTest": true,
            "GPS_HardwareSerial_LOCUS_DumpBasic": true,
            "GPS_HardwareSerial_LOCUS_Erase": true,
            "GPS_HardwareSerial_LOCUS_Start": true,
            "GPS_HardwareSerial_LOCUS_Status": true,
            "GPS_HardwareSerial_Parsing": true,
            "GPS_HardwareSerial_Timing": true,
            "GPS_I2C_EchoTest": true,
            "GPS_I2C_OLEDdebug": true,
            "GPS_I2C_Parsing": true,
            "GPS_SPI_EchoTest": true,
            "GPS_SoftwareSerial_EchoTest": false,
            "GPS_SoftwareSerial_LOCUS_DumpBasic": false,
            "GPS_SoftwareSerial_LOCUS_Erase": false,
            "GPS_SoftwareSerial_LOCUS_Start": false,
            "GPS_SoftwareSerial_LOCUS_Status": false,
            "GPS_SoftwareSerial_Parsing": false,
            "NMEA_EXTENSIONS": true,
            "blank": true,
            "shield_sdlog": false
          },
          "b5som": {
            "GPS_HardwareSerial_EchoTest": true,
            "GPS_HardwareSerial_LOCUS_DumpBasic": true,
            "GPS_HardwareSerial_LOCUS_Erase": true,
            "GPS_HardwareSerial_LOCUS_Start": true,
            "GPS_HardwareSerial_LOCUS_Status": true,
            "GPS_HardwareSerial_Parsing": true,
            "GPS_HardwareSerial_Timing": true,
            "GPS_I2C_EchoTest": true,
            "GPS_I2C_OLEDdebug": true,
            "GPS_I2C_Parsing": true,
            "GPS_SPI_EchoTest": true,
            "GPS_SoftwareSerial_EchoTest": false,
            "GPS_SoftwareSerial_LOCUS_DumpBasic": false,
            "GPS_SoftwareSerial_LOCUS_Erase": false,
            "GPS_SoftwareSerial_LOCUS_Start": false,
            "GPS_SoftwareSerial_LOCUS_Status": false,
            "GPS_SoftwareSerial_Parsing": false,
            "NMEA_EXTENSIONS": true,
            "blank": true,
            "shield_sdlog": false
          },
          "tracker": {
            "GPS_HardwareSerial_EchoTest": true,
            "GPS_HardwareSerial_LOCUS_DumpBasic": true,
            "GPS_HardwareSerial_LOCUS_Erase": true,
            "GPS_HardwareSerial_LOCUS_Start": true,
            "GPS_HardwareSerial_LOCUS_Status": true,
            "GPS_HardwareSerial_Parsing": true,
            "GPS_HardwareSerial_Timing": true,
            "GPS_I2C_EchoTest": true,
            "GPS_I2C_OLEDdebug": true,
            "GPS_I2C_Parsing": true,
            "GPS_SPI_EchoTest": true,
            "GPS_SoftwareSerial_EchoTest": false,
            "GPS_SoftwareSerial_LOCUS_DumpBasic": false,
            "GPS_SoftwareSerial_LOCUS_Erase": false,
            "GPS_SoftwareSerial_LOCUS_Start": false,
            "GPS_SoftwareSerial_LOCUS_Status": false,
            "GPS_SoftwareSerial_Parsing": false,
            "NMEA_EXTENSIONS": true,
            "blank": true,
            "shield_sdlog": false
          },
          "p2": {
            "GPS_HardwareSerial_EchoTest": true,
            "GPS_HardwareSerial_LOCUS_DumpBasic": true,
            "GPS_HardwareSerial_LOCUS_Erase": true,
            "GPS_HardwareSerial_LOCUS_Start": true,
            "GPS_HardwareSerial_LOCUS_Status": true,
            "GPS_HardwareSerial_Parsing": true,
            "GPS_HardwareSerial_Timing": true,
            "GPS_I2C_EchoTest": true,
            "GPS_I2C_OLEDdebug": true,
            "GPS_I2C_Parsing": true,
            "GPS_SPI_EchoTest": true,
            "GPS_SoftwareSerial_EchoTest": false,
            "GPS_SoftwareSerial_LOCUS_DumpBasic": false,
            "GPS_SoftwareSerial_LOCUS_Erase": false,
            "GPS_SoftwareSerial_LOCUS_Start": false,
            "GPS_SoftwareSerial_LOCUS_Status": false,
            "GPS_SoftwareSerial_Parsing": false,
            "NMEA_EXTENSIONS": true,
            "blank": true,
            "shield_sdlog": false
          },
          "msom": {
            "GPS_HardwareSerial_EchoTest": true,
            "GPS_HardwareSerial_LOCUS_DumpBasic": true,
            "GPS_HardwareSerial_LOCUS_Erase": true,
            "GPS_HardwareSerial_LOCUS_Start": true,
            "GPS_HardwareSerial_LOCUS_Status": true,
            "GPS_HardwareSerial_Parsing": true,
            "GPS_HardwareSerial_Timing": true,
            "GPS_I2C_EchoTest": true,
            "GPS_I2C_OLEDdebug": true,
            "GPS_I2C_Parsing": true,
            "GPS_SPI_EchoTest": true,
            "GPS_SoftwareSerial_EchoTest": false,
            "GPS_SoftwareSerial_LOCUS_DumpBasic": false,
            "GPS_SoftwareSerial_LOCUS_Erase": false,
            "GPS_SoftwareSerial_LOCUS_Start": false,
            "GPS_SoftwareSerial_LOCUS_Status": false,
            "GPS_SoftwareSerial_Parsing": false,
            "NMEA_EXTENSIONS": true,
            "blank": true,
            "shield_sdlog": false
          }
        },
        "5.6.0": {
          "argon": {
            "GPS_HardwareSerial_EchoTest": true,
            "GPS_HardwareSerial_LOCUS_DumpBasic": true,
            "GPS_HardwareSerial_LOCUS_Erase": true,
            "GPS_HardwareSerial_LOCUS_Start": true,
            "GPS_HardwareSerial_LOCUS_Status": true,
            "GPS_HardwareSerial_Parsing": true,
            "GPS_HardwareSerial_Timing": true,
            "GPS_I2C_EchoTest": true,
            "GPS_I2C_OLEDdebug": true,
            "GPS_I2C_Parsing": true,
            "GPS_SPI_EchoTest": true,
            "GPS_SoftwareSerial_EchoTest": false,
            "GPS_SoftwareSerial_LOCUS_DumpBasic": false,
            "GPS_SoftwareSerial_LOCUS_Erase": false,
            "GPS_SoftwareSerial_LOCUS_Start": false,
            "GPS_SoftwareSerial_LOCUS_Status": false,
            "GPS_SoftwareSerial_Parsing": false,
            "NMEA_EXTENSIONS": true,
            "blank": true,
            "shield_sdlog": false
          },
          "boron": {
            "GPS_HardwareSerial_EchoTest": true,
            "GPS_HardwareSerial_LOCUS_DumpBasic": true,
            "GPS_HardwareSerial_LOCUS_Erase": true,
            "GPS_HardwareSerial_LOCUS_Start": true,
            "GPS_HardwareSerial_LOCUS_Status": true,
            "GPS_HardwareSerial_Parsing": true,
            "GPS_HardwareSerial_Timing": true,
            "GPS_I2C_EchoTest": true,
            "GPS_I2C_OLEDdebug": true,
            "GPS_I2C_Parsing": true,
            "GPS_SPI_EchoTest": true,
            "GPS_SoftwareSerial_EchoTest": false,
            "GPS_SoftwareSerial_LOCUS_DumpBasic": false,
            "GPS_SoftwareSerial_LOCUS_Erase": false,
            "GPS_SoftwareSerial_LOCUS_Start": false,
            "GPS_SoftwareSerial_LOCUS_Status": false,
            "GPS_SoftwareSerial_Parsing": false,
            "NMEA_EXTENSIONS": true,
            "blank": true,
            "shield_sdlog": false
          },
          "bsom": {
            "GPS_HardwareSerial_EchoTest": true,
            "GPS_HardwareSerial_LOCUS_DumpBasic": true,
            "GPS_HardwareSerial_LOCUS_Erase": true,
            "GPS_HardwareSerial_LOCUS_Start": true,
            "GPS_HardwareSerial_LOCUS_Status": true,
            "GPS_HardwareSerial_Parsing": true,
            "GPS_HardwareSerial_Timing": true,
            "GPS_I2C_EchoTest": true,
            "GPS_I2C_OLEDdebug": true,
            "GPS_I2C_Parsing": true,
            "GPS_SPI_EchoTest": true,
            "GPS_SoftwareSerial_EchoTest": false,
            "GPS_SoftwareSerial_LOCUS_DumpBasic": false,
            "GPS_SoftwareSerial_LOCUS_Erase": false,
            "GPS_SoftwareSerial_LOCUS_Start": false,
            "GPS_SoftwareSerial_LOCUS_Status": false,
            "GPS_SoftwareSerial_Parsing": false,
            "NMEA_EXTENSIONS": true,
            "blank": true,
            "shield_sdlog": false
          },
          "b5som": {
            "GPS_HardwareSerial_EchoTest": true,
            "GPS_HardwareSerial_LOCUS_DumpBasic": true,
            "GPS_HardwareSerial_LOCUS_Erase": true,
            "GPS_HardwareSerial_LOCUS_Start": true,
            "GPS_HardwareSerial_LOCUS_Status": true,
            "GPS_HardwareSerial_Parsing": true,
            "GPS_HardwareSerial_Timing": true,
            "GPS_I2C_EchoTest": true,
            "GPS_I2C_OLEDdebug": true,
            "GPS_I2C_Parsing": true,
            "GPS_SPI_EchoTest": true,
            "GPS_SoftwareSerial_EchoTest": false,
            "GPS_SoftwareSerial_LOCUS_DumpBasic": false,
            "GPS_SoftwareSerial_LOCUS_Erase": false,
            "GPS_SoftwareSerial_LOCUS_Start": false,
            "GPS_SoftwareSerial_LOCUS_Status": false,
            "GPS_SoftwareSerial_Parsing": false,
            "NMEA_EXTENSIONS": true,
            "blank": true,
            "shield_sdlog": false
          },
          "tracker": {
            "GPS_HardwareSerial_EchoTest": true,
            "GPS_HardwareSerial_LOCUS_DumpBasic": true,
            "GPS_HardwareSerial_LOCUS_Erase": true,
            "GPS_HardwareSerial_LOCUS_Start": true,
            "GPS_HardwareSerial_LOCUS_Status": true,
            "GPS_HardwareSerial_Parsing": true,
            "GPS_HardwareSerial_Timing": true,
            "GPS_I2C_EchoTest": true,
            "GPS_I2C_OLEDdebug": true,
            "GPS_I2C_Parsing": true,
            "GPS_SPI_EchoTest": true,
            "GPS_SoftwareSerial_EchoTest": false,
            "GPS_SoftwareSerial_LOCUS_DumpBasic": false,
            "GPS_SoftwareSerial_LOCUS_Erase": false,
            "GPS_SoftwareSerial_LOCUS_Start": false,
            "GPS_SoftwareSerial_LOCUS_Status": false,
            "GPS_SoftwareSerial_Parsing": false,
            "NMEA_EXTENSIONS": true,
            "blank": true,
            "shield_sdlog": false
          },
          "p2": {
            "GPS_HardwareSerial_EchoTest": true,
            "GPS_HardwareSerial_LOCUS_DumpBasic": true,
            "GPS_HardwareSerial_LOCUS_Erase": true,
            "GPS_HardwareSerial_LOCUS_Start": true,
            "GPS_HardwareSerial_LOCUS_Status": true,
            "GPS_HardwareSerial_Parsing": true,
            "GPS_HardwareSerial_Timing": true,
            "GPS_I2C_EchoTest": true,
            "GPS_I2C_OLEDdebug": true,
            "GPS_I2C_Parsing": true,
            "GPS_SPI_EchoTest": true,
            "GPS_SoftwareSerial_EchoTest": false,
            "GPS_SoftwareSerial_LOCUS_DumpBasic": false,
            "GPS_SoftwareSerial_LOCUS_Erase": false,
            "GPS_SoftwareSerial_LOCUS_Start": false,
            "GPS_SoftwareSerial_LOCUS_Status": false,
            "GPS_SoftwareSerial_Parsing": false,
            "NMEA_EXTENSIONS": true,
            "blank": true,
            "shield_sdlog": false
          }
        },
        "4.2.0": {
          "argon": {
            "GPS_HardwareSerial_EchoTest": true,
            "GPS_HardwareSerial_LOCUS_DumpBasic": true,
            "GPS_HardwareSerial_LOCUS_Erase": true,
            "GPS_HardwareSerial_LOCUS_Start": true,
            "GPS_HardwareSerial_LOCUS_Status": true,
            "GPS_HardwareSerial_Parsing": true,
            "GPS_HardwareSerial_Timing": true,
            "GPS_I2C_EchoTest": true,
            "GPS_I2C_OLEDdebug": true,
            "GPS_I2C_Parsing": true,
            "GPS_SPI_EchoTest": true,
            "GPS_SoftwareSerial_EchoTest": false,
            "GPS_SoftwareSerial_LOCUS_DumpBasic": false,
            "GPS_SoftwareSerial_LOCUS_Erase": false,
            "GPS_SoftwareSerial_LOCUS_Start": false,
            "GPS_SoftwareSerial_LOCUS_Status": false,
            "GPS_SoftwareSerial_Parsing": false,
            "NMEA_EXTENSIONS": true,
            "blank": true,
            "shield_sdlog": false
          },
          "boron": {
            "GPS_HardwareSerial_EchoTest": true,
            "GPS_HardwareSerial_LOCUS_DumpBasic": true,
            "GPS_HardwareSerial_LOCUS_Erase": true,
            "GPS_HardwareSerial_LOCUS_Start": true,
            "GPS_HardwareSerial_LOCUS_Status": true,
            "GPS_HardwareSerial_Parsing": true,
            "GPS_HardwareSerial_Timing": true,
            "GPS_I2C_EchoTest": true,
            "GPS_I2C_OLEDdebug": true,
            "GPS_I2C_Parsing": true,
            "GPS_SPI_EchoTest": true,
            "GPS_SoftwareSerial_EchoTest": false,
            "GPS_SoftwareSerial_LOCUS_DumpBasic": false,
            "GPS_SoftwareSerial_LOCUS_Erase": false,
            "GPS_SoftwareSerial_LOCUS_Start": false,
            "GPS_SoftwareSerial_LOCUS_Status": false,
            "GPS_SoftwareSerial_Parsing": false,
            "NMEA_EXTENSIONS": true,
            "blank": true,
            "shield_sdlog": false
          },
          "bsom": {
            "GPS_HardwareSerial_EchoTest": true,
            "GPS_HardwareSerial_LOCUS_DumpBasic": true,
            "GPS_HardwareSerial_LOCUS_Erase": true,
            "GPS_HardwareSerial_LOCUS_Start": true,
            "GPS_HardwareSerial_LOCUS_Status": true,
            "GPS_HardwareSerial_Parsing": true,
            "GPS_HardwareSerial_Timing": true,
            "GPS_I2C_EchoTest": true,
            "GPS_I2C_OLEDdebug": true,
            "GPS_I2C_Parsing": true,
            "GPS_SPI_EchoTest": true,
            "GPS_SoftwareSerial_EchoTest": false,
            "GPS_SoftwareSerial_LOCUS_DumpBasic": false,
            "GPS_SoftwareSerial_LOCUS_Erase": false,
            "GPS_SoftwareSerial_LOCUS_Start": false,
            "GPS_SoftwareSerial_LOCUS_Status": false,
            "GPS_SoftwareSerial_Parsing": false,
            "NMEA_EXTENSIONS": true,
            "blank": true,
            "shield_sdlog": false
          },
          "b5som": {
            "GPS_HardwareSerial_EchoTest": true,
            "GPS_HardwareSerial_LOCUS_DumpBasic": true,
            "GPS_HardwareSerial_LOCUS_Erase": true,
            "GPS_HardwareSerial_LOCUS_Start": true,
            "GPS_HardwareSerial_LOCUS_Status": true,
            "GPS_HardwareSerial_Parsing": true,
            "GPS_HardwareSerial_Timing": true,
            "GPS_I2C_EchoTest": true,
            "GPS_I2C_OLEDdebug": true,
            "GPS_I2C_Parsing": true,
            "GPS_SPI_EchoTest": true,
            "GPS_SoftwareSerial_EchoTest": false,
            "GPS_SoftwareSerial_LOCUS_DumpBasic": false,
            "GPS_SoftwareSerial_LOCUS_Erase": false,
            "GPS_SoftwareSerial_LOCUS_Start": false,
            "GPS_SoftwareSerial_LOCUS_Status": false,
            "GPS_SoftwareSerial_Parsing": false,
            "NMEA_EXTENSIONS": true,
            "blank": true,
            "shield_sdlog": false
          },
          "tracker": {
            "GPS_HardwareSerial_EchoTest": true,
            "GPS_HardwareSerial_LOCUS_DumpBasic": true,
            "GPS_HardwareSerial_LOCUS_Erase": true,
            "GPS_HardwareSerial_LOCUS_Start": true,
            "GPS_HardwareSerial_LOCUS_Status": true,
            "GPS_HardwareSerial_Parsing": true,
            "GPS_HardwareSerial_Timing": true,
            "GPS_I2C_EchoTest": true,
            "GPS_I2C_OLEDdebug": true,
            "GPS_I2C_Parsing": true,
            "GPS_SPI_EchoTest": true,
            "GPS_SoftwareSerial_EchoTest": false,
            "GPS_SoftwareSerial_LOCUS_DumpBasic": false,
            "GPS_SoftwareSerial_LOCUS_Erase": false,
            "GPS_SoftwareSerial_LOCUS_Start": false,
            "GPS_SoftwareSerial_LOCUS_Status": false,
            "GPS_SoftwareSerial_Parsing": false,
            "NMEA_EXTENSIONS": true,
            "blank": true,
            "shield_sdlog": false
          },
          "esomx": {
            "GPS_HardwareSerial_EchoTest": true,
            "GPS_HardwareSerial_LOCUS_DumpBasic": true,
            "GPS_HardwareSerial_LOCUS_Erase": true,
            "GPS_HardwareSerial_LOCUS_Start": true,
            "GPS_HardwareSerial_LOCUS_Status": true,
            "GPS_HardwareSerial_Parsing": true,
            "GPS_HardwareSerial_Timing": true,
            "GPS_I2C_EchoTest": true,
            "GPS_I2C_OLEDdebug": true,
            "GPS_I2C_Parsing": true,
            "GPS_SPI_EchoTest": true,
            "GPS_SoftwareSerial_EchoTest": false,
            "GPS_SoftwareSerial_LOCUS_DumpBasic": false,
            "GPS_SoftwareSerial_LOCUS_Erase": false,
            "GPS_SoftwareSerial_LOCUS_Start": false,
            "GPS_SoftwareSerial_LOCUS_Status": false,
            "GPS_SoftwareSerial_Parsing": false,
            "NMEA_EXTENSIONS": true,
            "blank": true,
            "shield_sdlog": false
          }
        },
        "2.3.0": {
          "photon": {
            "GPS_HardwareSerial_EchoTest": true,
            "GPS_HardwareSerial_LOCUS_DumpBasic": true,
            "GPS_HardwareSerial_LOCUS_Erase": true,
            "GPS_HardwareSerial_LOCUS_Start": true,
            "GPS_HardwareSerial_LOCUS_Status": true,
            "GPS_HardwareSerial_Parsing": true,
            "GPS_HardwareSerial_Timing": true,
            "GPS_I2C_EchoTest": true,
            "GPS_I2C_OLEDdebug": true,
            "GPS_I2C_Parsing": true,
            "GPS_SPI_EchoTest": true,
            "GPS_SoftwareSerial_EchoTest": false,
            "GPS_SoftwareSerial_LOCUS_DumpBasic": false,
            "GPS_SoftwareSerial_LOCUS_Erase": false,
            "GPS_SoftwareSerial_LOCUS_Start": false,
            "GPS_SoftwareSerial_LOCUS_Status": false,
            "GPS_SoftwareSerial_Parsing": false,
            "NMEA_EXTENSIONS": true,
            "blank": true,
            "shield_sdlog": false
          },
          "electron": {
            "GPS_HardwareSerial_EchoTest": true,
            "GPS_HardwareSerial_LOCUS_DumpBasic": true,
            "GPS_HardwareSerial_LOCUS_Erase": true,
            "GPS_HardwareSerial_LOCUS_Start": true,
            "GPS_HardwareSerial_LOCUS_Status": true,
            "GPS_HardwareSerial_Parsing": true,
            "GPS_HardwareSerial_Timing": true,
            "GPS_I2C_EchoTest": true,
            "GPS_I2C_OLEDdebug": true,
            "GPS_I2C_Parsing": true,
            "GPS_SPI_EchoTest": true,
            "GPS_SoftwareSerial_EchoTest": false,
            "GPS_SoftwareSerial_LOCUS_DumpBasic": false,
            "GPS_SoftwareSerial_LOCUS_Erase": false,
            "GPS_SoftwareSerial_LOCUS_Start": false,
            "GPS_SoftwareSerial_LOCUS_Status": false,
            "GPS_SoftwareSerial_Parsing": false,
            "NMEA_EXTENSIONS": true,
            "blank": true,
            "shield_sdlog": false
          }
        }
      }
    }
  },
  "readme": "# Adafruit_GPS [![Build Status](https://travis-ci.com/adafruit/Adafruit_GPS.svg?branch=master)](https://travis-ci.com/adafruit/Adafruit_GPS) [![Documentation](https://github.com/adafruit/ci-arduino/blob/master/assets/doxygen_badge.svg)](http://adafruit.github.io/Adafruit_GPS/html/index.html)\n\n> **Warning**\n>\n> This library assumes that only valid, supported NMEA sentences are parsed.\n> Parsing invalid or unsupported NMEA sentences may result in memory corruption and/or unhandled faults & exceptions!\n\nThis is the Adafruit GPS library - the ultimate GPS library\nfor the ultimate GPS module!\n\nTested and works great with the Adafruit Ultimate GPS module\nusing MTK33x9 chipset\n------> http://www.adafruit.com/products/746\n\nThese modules use TTL serial to communicate, 2 pins are required to\ninterface.\n\nAdafruit invests time and resources providing this open source code,\nplease support Adafruit and open-source hardware by purchasing\nproducts from Adafruit!\n\nWritten by Limor Fried/Ladyada  for Adafruit Industries.\nBSD license, check license.txt for more information\nAll text above must be included in any redistribution\n\nTo install, use the Arduino Library Manager to search for 'Adafruit GPS' and install the library.\n",
  "allVersions": [
    "1.7.5"
  ]
}