{
  "items": [
    {
      "dir": "hardware",
      "isSection": true
    },
    [
      {
        "dir": "hardware-overview",
        "title": "Hardware overview",
        "href": "/getting-started/hardware/hardware-overview/"
      },
      {
        "dir": "tracking-system",
        "title": "Tracking system",
        "href": "/getting-started/hardware/tracking-system"
      },
      {
        "dir": "cellular-overview",
        "title": "Cellular overview",
        "href": "/getting-started/hardware/cellular-overview/"
      }
    ]
  ]
}